<BackupInst xmlns="http://www.microsoft.com/GroupPolicy/GPOOperations/Manifest"><GPOGuid><![CDATA[{D59C190F-F043-4F2E-B211-C3431A65A6C8}]]></GPOGuid><GPODomain><![CDATA[sigma.local]]></GPODomain><GPODomainGuid><![CDATA[{d4ad5f04-ee39-4215-9ef8-f93bff4d7eab}]]></GPODomainGuid><GPODomainController><![CDATA[SS0001.sigma.local]]></GPODomainController><BackupTime><![CDATA[2022-11-01T12:21:38]]></BackupTime><ID><![CDATA[{7584BBF2-BD34-47F1-AE84-E99DE2E2F766}]]></ID><Comment><![CDATA[]]></Comment><GPODisplayName><![CDATA[GPO-Regional Settings-SE]]></GPODisplayName></BackupInst>
